seed_services_client/__init__.py
seed_services_client/__version__.py
seed_services_client/auth.py
seed_services_client/control_interface.py
seed_services_client/hub.py
seed_services_client/identity_store.py
seed_services_client/message_sender.py
seed_services_client/metrics.py
seed_services_client/scheduler.py
seed_services_client/seed_services.py
seed_services_client/service_rating.py
seed_services_client/stage_based_messaging.py
seed_services_client/utils.py
seed_services_client-0.37.2.dist-info/LICENSE
seed_services_client-0.37.2.dist-info/METADATA
seed_services_client-0.37.2.dist-info/WHEEL
seed_services_client-0.37.2.dist-info/top_level.txt
seed_services_client-0.37.2.dist-info/RECORD
