Metadata-Version: 1.1
Name: seed-services-client
Version: 0.37.2
Summary: Python client for Seed Service REST APIs
Home-page: https://github.com/praekeltfoundation/seed-services-client
Author: Praekelt Foundation and Individual Contributors
Author-email: dev@praekeltfoundation.org
License: BSD
Keywords: seed-services-client
Platform: UNKNOWN
Classifier: Intended Audience :: Developers
Classifier: Natural Language :: English
Classifier: Programming Language :: Python :: 2.7
